{
    "quizzes": [
        {
            "id": "2005050",
            "mondai": "東京本社と各支店間を直接接続している通信ネットワークに，回線多重化装置(図の●印)を導入し，通信ネットワークのコストダウンを図った。このときの月額経済効果は何万円か。ここで，新旧ネットワークの各支店間の月額回線費用(万円)は図に示すとおりである。また，回線多重化装置は1台300万円の装置を月額料率2％のリース契約で2台導入することにし，モデムなどの通信装置の金額は無視する。<div class=\"img_margin\"><img data-image-index=\"0\"></div>",
            "sentaku": [
                "10",
                "13",
                "15",
                "19"
            ],
            "answer": 1
        }
    ]
}